LICENSE
MANIFEST.in
README.md
requirements.txt
setup.py
pyauto/__init__.py
pyauto.filecache.egg-info/PKG-INFO
pyauto.filecache.egg-info/SOURCES.txt
pyauto.filecache.egg-info/dependency_links.txt
pyauto.filecache.egg-info/requires.txt
pyauto.filecache.egg-info/top_level.txt
pyauto/filecache/__init__.py
pyauto/filecache/commands.py
pyauto/filecache/config.py