Metadata-Version: 1.0
Name: pyauto.filecache
Version: 0.0.2
Summary: A simple module to download and cache files
Home-page: https://github.com/adamjaso/pyauto/tree/master/filecache
Author: Adam Jaso
Author-email: UNKNOWN
License: GNU General Public License V2
Platform: UNKNOWN
